{"id":"d26f7508-2f09-4146-b01b-25a0eec192c3","name":"0주차-0-카페","cuts":[{"_v":4,"id":"bb64e0d2-fda3-4952-ba87-5d36310d9daa","line":"","character_name":"","screen_graphics":[{"Image":{"id":"e5e26629-e5e2-6629-e5e2-6629e5e26629","circumscribed":{"center_xy":{"x":55.38857,"y":48.888905},"radius":107.610565}}}]},{"_v":4,"id":"33f9961e-3897-46a8-a798-09c5079b18e5","line":"아 네, 부장님, 잠시만요!","character_name":"피디","screen_graphics":[{"Image":{"id":"e5e26629-e5e2-6629-e5e2-6629e5e26629","circumscribed":{"center_xy":{"x":55.38857,"y":48.888905},"radius":107.610565}}}]},{"_v":4,"id":"e26049af-ca94-4def-ac4c-8272e55cd7d9","line":"안녕하세요, 주문하시겠어요?","character_name":"카페 직원","screen_graphics":[{"Image":{"id":"e5e26629-e5e2-6629-e5e2-6629e5e26629","circumscribed":{"center_xy":{"x":55.38857,"y":48.888905},"radius":107.610565}}},{"Image":{"id":"b985f569-b985-f569-b985-f569b985f569","circumscribed":{"center_xy":{"x":51.86059,"y":58.877018},"radius":80.95909}}}]},{"_v":4,"id":"33779ee9-668b-4019-b0cb-5a2b93e7329c","line":"(소곤소곤) 아이스 아메리카노 4잔 포장이요!","character_name":"피디","screen_graphics":[{"Image":{"id":"e5e26629-e5e2-6629-e5e2-6629e5e26629","circumscribed":{"center_xy":{"x":55.38857,"y":48.888905},"radius":107.610565}}},{"Image":{"id":"b985f569-b985-f569-b985-f569b985f569","circumscribed":{"center_xy":{"x":51.86059,"y":58.877018},"radius":80.95909}}}]},{"_v":4,"id":"f569f862-9513-4f6f-b85c-5873b96c6a88","line":"네 네, 부장님, 그래서 지난번에 제가 소개시켜드린...","character_name":"피디","screen_graphics":[{"Image":{"id":"e5e26629-e5e2-6629-e5e2-6629e5e26629","circumscribed":{"center_xy":{"x":55.38857,"y":48.888905},"radius":107.610565}}},{"Image":{"id":"b985f569-b985-f569-b985-f569b985f569","circumscribed":{"center_xy":{"x":51.86059,"y":58.877018},"radius":80.95909}}}]},{"_v":4,"id":"cabaad51-7e59-40db-8fea-3552a492aee0","line":"포인트 카드 있으세요?","character_name":"카페 직원","screen_graphics":[{"Image":{"id":"e5e26629-e5e2-6629-e5e2-6629e5e26629","circumscribed":{"center_xy":{"x":55.38857,"y":48.888905},"radius":107.610565}}},{"Image":{"id":"b985f569-b985-f569-b985-f569b985f569","circumscribed":{"center_xy":{"x":51.86059,"y":58.877018},"radius":80.95909}}}]},{"_v":4,"id":"2cf44516-6d31-4bdb-87cb-3969ee8f5bbe","line":"(도리도리) 아 네 그때 그 건 말인데요,","character_name":"피디","screen_graphics":[{"Image":{"id":"e5e26629-e5e2-6629-e5e2-6629e5e26629","circumscribed":{"center_xy":{"x":55.38857,"y":48.888905},"radius":107.610565}}},{"Image":{"id":"b985f569-b985-f569-b985-f569b985f569","circumscribed":{"center_xy":{"x":51.86059,"y":58.877018},"radius":80.95909}}}]},{"_v":4,"id":"61a589c0-3cd6-44b7-8b42-40897d3a9b71","line":"네, 포인트는 안하시구요, 16,000원입니다!","character_name":"카페 직원","screen_graphics":[{"Image":{"id":"e5e26629-e5e2-6629-e5e2-6629e5e26629","circumscribed":{"center_xy":{"x":55.38857,"y":48.888905},"radius":107.610565}}},{"Image":{"id":"b985f569-b985-f569-b985-f569b985f569","circumscribed":{"center_xy":{"x":51.86059,"y":58.877018},"radius":80.95909}}}]},{"_v":4,"id":"48be170a-c399-4742-99f7-6e72df57acdd","line":"말도 안돼요!","character_name":"오하연","screen_graphics":[{"Image":{"id":"e5e26629-e5e2-6629-e5e2-6629e5e26629","circumscribed":{"center_xy":{"x":55.38857,"y":48.888905},"radius":107.610565}}}]},{"_v":4,"id":"1a076c96-c716-4beb-aa5d-9ae9a5b2c22b","line":"말도 안돼요!","character_name":"오하연","screen_graphics":[{"Image":{"id":"e5e26629-e5e2-6629-e5e2-6629e5e26629","circumscribed":{"center_xy":{"x":55.38857,"y":48.888905},"radius":107.610565}}},{"Cg":{"id":"5a5ec517-9f14-fa32-02d9-3c313c758929","part_variants":[["f87e024f-7006-4fb8-79f9-72b3afa0a2db",{"Xywh":{"x":29.481133,"y":24.188177,"width":42.21698,"height":10.782681}}],["45b5b291-3e9c-d660-dc8b-9a7a826c6d50",{"Xywh":{"x":33.195755,"y":33.597004,"width":36.96934,"height":8.617819}}],["12e7316b-6f1c-788d-7e76-ff7b1effeae4",{"Xywh":{"x":35.49528,"y":30.141548,"width":29.658018,"height":16.90258}}],["f04ae463-0a5d-9102-f99d-ac00a77f7b80",{"Xywh":{"x":5.0707545,"y":2.2897584,"width":87.38207,"height":96.62781}}],["51fd3950-9bfb-62e6-4c01-06a6d7903b50",{"Xywh":{"x":39.209908,"y":44.504578,"width":2.8301888,"height":3.5387177}}],["45e8efae-5d34-ed65-12a1-f550266a1f08",{"Xywh":{"x":5.0707545,"y":2.2897584,"width":87.38207,"height":96.62781}}],["06b4597e-ee04-0d37-a3fa-cc1b35dd4ff2",{"Xywh":{"x":5.129717,"y":2.2897584,"width":87.32311,"height":96.62781}}]],"circumscribed":{"center_xy":{"x":52.214985,"y":46.300583},"radius":78.88254}}}]},{"_v":4,"id":"474d09f0-6b00-40f2-bf03-4785265497c2","line":"... 아무튼 그런 이유로 하연씨와 계약은 해지입니다.","character_name":"MCN 담당자","screen_graphics":[{"Image":{"id":"e5e26629-e5e2-6629-e5e2-6629e5e26629","circumscribed":{"center_xy":{"x":55.38857,"y":48.888905},"radius":107.610565}}},{"Cg":{"id":"5a5ec517-9f14-fa32-02d9-3c313c758929","part_variants":[["f87e024f-7006-4fb8-79f9-72b3afa0a2db",{"Xywh":{"x":29.481133,"y":24.188177,"width":42.21698,"height":10.782681}}],["45b5b291-3e9c-d660-dc8b-9a7a826c6d50",{"Xywh":{"x":33.195755,"y":33.597004,"width":36.96934,"height":8.617819}}],["12e7316b-6f1c-788d-7e76-ff7b1effeae4",{"Xywh":{"x":35.49528,"y":30.141548,"width":29.658018,"height":16.90258}}],["f04ae463-0a5d-9102-f99d-ac00a77f7b80",{"Xywh":{"x":5.0707545,"y":2.2897584,"width":87.38207,"height":96.62781}}],["51fd3950-9bfb-62e6-4c01-06a6d7903b50",{"Xywh":{"x":39.209908,"y":44.504578,"width":2.8301888,"height":3.5387177}}],["45e8efae-5d34-ed65-12a1-f550266a1f08",{"Xywh":{"x":5.0707545,"y":2.2897584,"width":87.38207,"height":96.62781}}],["06b4597e-ee04-0d37-a3fa-cc1b35dd4ff2",{"Xywh":{"x":5.129717,"y":2.2897584,"width":87.32311,"height":96.62781}}]],"circumscribed":{"center_xy":{"x":76.82593,"y":47.474396},"radius":78.88254}}},{"Cg":{"id":"54ecccfd-ac21-b9b5-2851-2c6d527fd424","part_variants":[["cb45f180-427e-3d4f-4aa0-69590030d99b",{"Xywh":{"x":25.278324,"y":28.827702,"width":32.61297,"height":3.838131}}],["795a2efb-d3dc-2fdd-4fcf-e53f59a85790",{"Xywh":{"x":28.028814,"y":31.706299,"width":29.600523,"height":7.467668}}],["23525677-d717-8052-a133-6248503e9d5b",{"Xywh":{"x":39.423706,"y":41.13475,"width":9.495744,"height":3.838131}}],["dc0b5563-736f-4cbb-edcc-dd5c5324e30b",{"Xywh":{"x":40.929928,"y":39.257404,"width":0.5239031,"height":0.33375052}}],["9f38570f-83f8-eb72-4c36-e7dd776b58fe",{"Xywh":{"x":30.38638,"y":39.215687,"width":22.26588,"height":3.2123487}}],["f2743637-5500-018a-0f24-29f1d62025a0",{"Xywh":{"x":1.5717093,"y":1.3350021,"width":101.440735,"height":104.50563}}],["6c567145-fb37-7902-d9cc-4997fba4324d",{"Xywh":{"x":1.6371971,"y":1.3350021,"width":98.3628,"height":98.665}}]],"circumscribed":{"center_xy":{"x":30.595337,"y":39.361874},"radius":35.07009}}}]},{"_v":4,"id":"6e1824e2-8bb3-4c36-ad49-e961128e7aee","line":"에이있!!@#!$","character_name":"오하연","screen_graphics":[{"Image":{"id":"e5e26629-e5e2-6629-e5e2-6629e5e26629","circumscribed":{"center_xy":{"x":55.38857,"y":48.888905},"radius":107.610565}}},{"Cg":{"id":"5a5ec517-9f14-fa32-02d9-3c313c758929","part_variants":[["f87e024f-7006-4fb8-79f9-72b3afa0a2db",{"Xywh":{"x":29.481133,"y":24.188177,"width":42.21698,"height":10.782681}}],["45b5b291-3e9c-d660-dc8b-9a7a826c6d50",{"Xywh":{"x":33.195755,"y":33.597004,"width":36.96934,"height":8.617819}}],["12e7316b-6f1c-788d-7e76-ff7b1effeae4",{"Xywh":{"x":35.49528,"y":30.141548,"width":29.658018,"height":16.90258}}],["f04ae463-0a5d-9102-f99d-ac00a77f7b80",{"Xywh":{"x":5.0707545,"y":2.2897584,"width":87.38207,"height":96.62781}}],["51fd3950-9bfb-62e6-4c01-06a6d7903b50",{"Xywh":{"x":39.209908,"y":44.504578,"width":2.8301888,"height":3.5387177}}],["45e8efae-5d34-ed65-12a1-f550266a1f08",{"Xywh":{"x":5.0707545,"y":2.2897584,"width":87.38207,"height":96.62781}}],["06b4597e-ee04-0d37-a3fa-cc1b35dd4ff2",{"Xywh":{"x":5.129717,"y":2.2897584,"width":87.32311,"height":96.62781}}]],"circumscribed":{"center_xy":{"x":75.02256,"y":48.8888},"radius":78.88254}}},{"Cg":{"id":"54ecccfd-ac21-b9b5-2851-2c6d527fd424","part_variants":[["cb45f180-427e-3d4f-4aa0-69590030d99b",{"Xywh":{"x":25.278324,"y":28.827702,"width":32.61297,"height":3.838131}}],["795a2efb-d3dc-2fdd-4fcf-e53f59a85790",{"Xywh":{"x":28.028814,"y":31.706299,"width":29.600523,"height":7.467668}}],["23525677-d717-8052-a133-6248503e9d5b",{"Xywh":{"x":39.423706,"y":41.13475,"width":9.495744,"height":3.838131}}],["dc0b5563-736f-4cbb-edcc-dd5c5324e30b",{"Xywh":{"x":40.929928,"y":39.257404,"width":0.5239031,"height":0.33375052}}],["9f38570f-83f8-eb72-4c36-e7dd776b58fe",{"Xywh":{"x":30.38638,"y":39.215687,"width":22.26588,"height":3.2123487}}],["f2743637-5500-018a-0f24-29f1d62025a0",{"Xywh":{"x":1.5717093,"y":1.3350021,"width":101.440735,"height":104.50563}}],["6c567145-fb37-7902-d9cc-4997fba4324d",{"Xywh":{"x":1.6371971,"y":1.3350021,"width":98.3628,"height":98.665}}]],"circumscribed":{"center_xy":{"x":30.595337,"y":39.361874},"radius":35.07009}}}]},{"_v":4,"id":"0c341568-73f7-47f9-986b-c5d54b8723a9","line":"","character_name":"","screen_graphics":[{"Image":{"id":"e5e26629-e5e2-6629-e5e2-6629e5e26629","circumscribed":{"center_xy":{"x":55.38857,"y":48.888905},"radius":107.610565}}},{"Image":{"id":"71f6d716-71f6-d716-71f6-d71671f6d716","circumscribed":{"center_xy":{"x":50.00001,"y":37.322826},"radius":72.189865}}}]},{"_v":4,"id":"e28c69f4-a583-493b-b6c0-3faca81042ed","line":"읍... 푸후... 하연씨, 이러시면 더더욱 문제를 심각하게 만들 뿐이에요.","character_name":"MCN 담당자","screen_graphics":[{"Image":{"id":"e5e26629-e5e2-6629-e5e2-6629e5e26629","circumscribed":{"center_xy":{"x":55.38857,"y":48.888905},"radius":107.610565}}},{"Image":{"id":"a50a39f5-a50a-39f5-a50a-39f5a50a39f5","circumscribed":{"center_xy":{"x":49.999966,"y":37.298225},"radius":72.197716}}}]},{"_v":4,"id":"70089b55-333e-4600-8613-ba078aed32ac","line":"으아아앙!!! 에이이있@!$!@%!","character_name":"오하연","screen_graphics":[{"Image":{"id":"e5e26629-e5e2-6629-e5e2-6629e5e26629","circumscribed":{"center_xy":{"x":55.38857,"y":48.888905},"radius":107.610565}}},{"Image":{"id":"e157b3de-e157-b3de-e157-b3dee157b3de","circumscribed":{"center_xy":{"x":50.00001,"y":37.31837},"radius":72.18689}}}]},{"_v":4,"id":"705b3b36-d896-4489-a857-b79d8e512d57","line":"푸슈~","character_name":"","screen_graphics":[{"Image":{"id":"e5e26629-e5e2-6629-e5e2-6629e5e26629","circumscribed":{"center_xy":{"x":55.38857,"y":48.888905},"radius":107.610565}}},{"Image":{"id":"8fd3ee17-8fd3-ee17-8fd3-ee178fd3ee17","circumscribed":{"center_xy":{"x":50.00001,"y":37.31837},"radius":72.18689}}}]},{"_v":4,"id":"6f4138cb-3eac-438e-b385-5a75e2dfcee2","line":"막았어!?!?","character_name":"오하연","screen_graphics":[{"Image":{"id":"e5e26629-e5e2-6629-e5e2-6629e5e26629","circumscribed":{"center_xy":{"x":55.38857,"y":48.888905},"radius":107.610565}}},{"Image":{"id":"7efd7abe-7efd-7abe-7efd-7abe7efd7abe","circumscribed":{"center_xy":{"x":50.00001,"y":37.31837},"radius":72.18689}}}]},{"_v":4,"id":"74044db9-6f4c-4e55-8dc6-bdd33549639b","line":"하연씨, 철좀 들으세요.","character_name":"MCN 담당자","screen_graphics":[{"Image":{"id":"e5e26629-e5e2-6629-e5e2-6629e5e26629","circumscribed":{"center_xy":{"x":55.38857,"y":48.888905},"radius":107.610565}}},{"Image":{"id":"7efd7abe-7efd-7abe-7efd-7abe7efd7abe","circumscribed":{"center_xy":{"x":50.00001,"y":37.31837},"radius":72.18689}}}]},{"_v":4,"id":"ab35930f-3a9d-4d10-9e61-109df101b384","line":"계약 해지 관련 서류는 여기 놓고 가겠습니다.","character_name":"MCN 담당자","screen_graphics":[{"Image":{"id":"e5e26629-e5e2-6629-e5e2-6629e5e26629","circumscribed":{"center_xy":{"x":55.38857,"y":48.888905},"radius":107.610565}}},{"Cg":{"id":"1eb4357c-0ee3-9088-4bdc-009701346974","part_variants":[["bdd19300-7c6f-886c-d13b-fe75f286087a",{"Xywh":{"x":50.97113,"y":36.733917,"width":1.2598425,"height":1.8271793}}],["4c726a6d-4f98-bf9c-f753-7c742e0a08d3",{"Xywh":{"x":26.71916,"y":27.71222,"width":26.824146,"height":4.9866767}}],["058082cf-b958-83e2-cf12-338dcfcd8d9a",{"Xywh":{"x":28.871391,"y":29.311,"width":26.24672,"height":8.222307}}],["5b3476cd-f7d1-3743-9cb8-2f20c912a735",{"Xywh":{"x":40.997375,"y":37.571373,"width":0.2624672,"height":0.3425961}}],["cf427047-3811-31c0-846c-9ea92814fc80",{"Xywh":{"x":40.31496,"y":38.789494,"width":7.1391077,"height":3.4640274}}],["59b3c646-a482-444a-af16-c3e879015e0e",{"Xywh":{"x":13.28084,"y":4.4918156,"width":76.53543,"height":85.458694}}],["2f7421db-62fd-57ce-f801-2c7d5a7022b7",{"Xywh":{"x":13.28084,"y":4.529882,"width":76.48294,"height":87.24781}}]],"circumscribed":{"center_xy":{"x":50.00001,"y":37.31837},"radius":72.18689}}}]},{"_v":4,"id":"005bfe29-8e3b-4c3e-b7d0-8ea1691ced29","line":"으허허엉 가지마!!! 내가 잘할게!!!\n내가 방송에서 욕 안하면 되는거잖아!!!","character_name":"오하연","screen_graphics":[{"Image":{"id":"e5e26629-e5e2-6629-e5e2-6629e5e26629","circumscribed":{"center_xy":{"x":55.38857,"y":48.888905},"radius":107.610565}}},{"Image":{"id":"00580266-0058-0266-0058-026600580266","circumscribed":{"center_xy":{"x":50.00001,"y":37.31837},"radius":72.18689}}}]}]}