{
  "tracks": [
    {
      "Camera": {
        "id": "camera-track",
        "clips": [
          {
            "id": "CameraClip-L91OkHeBcvsWwweDWQbLV",
            "start_at": {
              "Ms": 0.0
            },
            "end_at": {
              "Ms": 3150.0
            },
            "camera_angle": {
              "character": {
                "character_pose_emotion": [
                  "하연",
                  "앉아두손모으고",
                  "웃음"
                ],
                "source_01_circumscribed": {
                  "center": {
                    "x": 0.48333332,
                    "y": 0.65555555
                  },
                  "radius": 0.4326241
                },
                "crop_screen_01_rect": {
                  "Ltrb": {
                    "left": 0.0,
                    "top": 0.0,
                    "right": 1.0,
                    "bottom": 1.0
                  }
                }
              },
              "background": null
            }
          },
          {
            "id": "CameraClip-jjZ4735B8NP9yLRAVOt6M",
            "start_at": {
              "Ms": 3150.0
            },
            "end_at": {
              "Ms": 4910.0
            },
            "camera_angle": {
              "character": {
                "character_pose_emotion": [
                  "피디",
                  "기본",
                  "의심"
                ],
                "source_01_circumscribed": {
                  "center": {
                    "x": 0.49375,
                    "y": 0.85555553
                  },
                  "radius": 0.5
                },
                "crop_screen_01_rect": {
                  "Ltrb": {
                    "left": 0.0,
                    "top": 0.0,
                    "right": 1.0,
                    "bottom": 1.0
                  }
                }
              },
              "background": null
            }
          },
          {
            "id": "CameraClip-qu-k5c9eOogo8GBKKGtv4",
            "start_at": {
              "Ms": 4910.0
            },
            "end_at": {
              "Ms": 5980.0
            },
            "camera_angle": {
              "character": {
                "character_pose_emotion": [
                  "하연",
                  "앉아두손모으고",
                  "웃음"
                ],
                "source_01_circumscribed": {
                  "center": {
                    "x": 0.48333332,
                    "y": 0.65555555
                  },
                  "radius": 0.4326241
                },
                "crop_screen_01_rect": {
                  "Ltrb": {
                    "left": 0.0,
                    "top": 0.0,
                    "right": 1.0,
                    "bottom": 1.0
                  }
                }
              },
              "background": null
            }
          },
          {
            "id": "CameraClip-OdGF-PSS8HuCUtBf_fY_U",
            "start_at": {
              "Ms": 5980.0
            },
            "end_at": {
              "Ms": 8590.0
            },
            "camera_angle": {
              "character": {
                "character_pose_emotion": [
                  "피디",
                  "기본",
                  "의심"
                ],
                "source_01_circumscribed": {
                  "center": {
                    "x": 0.49375,
                    "y": 0.85555553
                  },
                  "radius": 0.5
                },
                "crop_screen_01_rect": {
                  "Ltrb": {
                    "left": 0.0,
                    "top": 0.0,
                    "right": 1.0,
                    "bottom": 1.0
                  }
                }
              },
              "background": null
            }
          },
          {
            "id": "CameraClip-iTg3O_N9vMX02IOaHygON",
            "start_at": {
              "Ms": 8590.0
            },
            "end_at": {
              "Ms": 10980.0
            },
            "camera_angle": {
              "character": {
                "character_pose_emotion": [
                  "하연",
                  "앉아두손모으고",
                  "걱정"
                ],
                "source_01_circumscribed": {
                  "center": {
                    "x": 0.48333332,
                    "y": 0.65555555
                  },
                  "radius": 0.4326241
                },
                "crop_screen_01_rect": {
                  "Ltrb": {
                    "left": 0.0,
                    "top": 0.0,
                    "right": 1.0,
                    "bottom": 1.0
                  }
                }
              },
              "background": null
            }
          },
          {
            "id": "CameraClip-YTr_O9hy9k5VNHe34Zjx9",
            "start_at": {
              "Ms": 10980.0
            },
            "end_at": {
              "Ms": 13170.0
            },
            "camera_angle": {
              "character": {
                "character_pose_emotion": [
                  "피디",
                  "기본",
                  "눈감음"
                ],
                "source_01_circumscribed": {
                  "center": {
                    "x": 0.49375,
                    "y": 0.85555553
                  },
                  "radius": 0.5
                },
                "crop_screen_01_rect": {
                  "Ltrb": {
                    "left": 0.0,
                    "top": 0.0,
                    "right": 1.0,
                    "bottom": 1.0
                  }
                }
              },
              "background": null
            }
          },
          {
            "id": "CameraClip-Tf8Edjy1I6TKW1BebZar-",
            "start_at": {
              "Ms": 13170.0
            },
            "end_at": {
              "Ms": 15190.0
            },
            "camera_angle": {
              "character": {
                "character_pose_emotion": [
                  "하연",
                  "앉아두손모으고",
                  "웃음"
                ],
                "source_01_circumscribed": {
                  "center": {
                    "x": 0.48333332,
                    "y": 0.65555555
                  },
                  "radius": 0.4326241
                },
                "crop_screen_01_rect": {
                  "Ltrb": {
                    "left": 0.0,
                    "top": 0.0,
                    "right": 1.0,
                    "bottom": 1.0
                  }
                }
              },
              "background": null
            }
          },
          {
            "id": "CameraClip-_ABbukQ6XGG3ZRc-Cbd4K",
            "start_at": {
              "Ms": 15190.0
            },
            "end_at": {
              "Ms": 17120.0
            },
            "camera_angle": {
              "character": {
                "character_pose_emotion": [
                  "피디",
                  "기본",
                  "당황"
                ],
                "source_01_circumscribed": {
                  "center": {
                    "x": 0.49375,
                    "y": 0.85555553
                  },
                  "radius": 0.5
                },
                "crop_screen_01_rect": {
                  "Ltrb": {
                    "left": 0.0,
                    "top": 0.0,
                    "right": 1.0,
                    "bottom": 1.0
                  }
                }
              },
              "background": null
            }
          },
          {
            "id": "CameraClip-gjhGFW1YiSlTUHQKMOcna",
            "start_at": {
              "Ms": 17120.0
            },
            "end_at": {
              "Ms": 20020.0
            },
            "camera_angle": {
              "character": {
                "character_pose_emotion": [
                  "하연",
                  "앉아두손모으고",
                  "걱정"
                ],
                "source_01_circumscribed": {
                  "center": {
                    "x": 0.48333332,
                    "y": 0.65555555
                  },
                  "radius": 0.4326241
                },
                "crop_screen_01_rect": {
                  "Ltrb": {
                    "left": 0.0,
                    "top": 0.0,
                    "right": 1.0,
                    "bottom": 1.0
                  }
                }
              },
              "background": null
            }
          },
          {
            "id": "CameraClip-cLXcFmgC83lPJCcAVavmI",
            "start_at": {
              "Ms": 20020.0
            },
            "end_at": {
              "Ms": 21960.0
            },
            "camera_angle": {
              "character": {
                "character_pose_emotion": [
                  "피디",
                  "기본",
                  "눈치"
                ],
                "source_01_circumscribed": {
                  "center": {
                    "x": 0.49375,
                    "y": 0.85555553
                  },
                  "radius": 0.5
                },
                "crop_screen_01_rect": {
                  "Ltrb": {
                    "left": 0.0,
                    "top": 0.0,
                    "right": 1.0,
                    "bottom": 1.0
                  }
                }
              },
              "background": null
            }
          },
          {
            "id": "CameraClip-ufeTuFB2KqTuVmbodoatg",
            "start_at": {
              "Ms": 21960.0
            },
            "end_at": {
              "Ms": 23610.0
            },
            "camera_angle": {
              "character": {
                "character_pose_emotion": [
                  "하연",
                  "허리에손주먹",
                  "화남"
                ],
                "source_01_circumscribed": {
                  "center": {
                    "x": 0.48333332,
                    "y": 0.65555555
                  },
                  "radius": 0.4326241
                },
                "crop_screen_01_rect": {
                  "Ltrb": {
                    "left": 0.0,
                    "top": 0.0,
                    "right": 1.0,
                    "bottom": 1.0
                  }
                }
              },
              "background": null
            }
          },
          {
            "id": "CameraClip-AhTT6a3g9SKX-g300zczb",
            "start_at": {
              "Ms": 23610.0
            },
            "end_at": {
              "Ms": 26180.0
            },
            "camera_angle": {
              "character": {
                "character_pose_emotion": [
                  "피디",
                  "기본",
                  "무표정"
                ],
                "source_01_circumscribed": {
                  "center": {
                    "x": 0.49375,
                    "y": 0.85555553
                  },
                  "radius": 0.5
                },
                "crop_screen_01_rect": {
                  "Ltrb": {
                    "left": 0.0,
                    "top": 0.0,
                    "right": 1.0,
                    "bottom": 1.0
                  }
                }
              },
              "background": null
            }
          },
          {
            "id": "CameraClip-qUkEvdy0nEpPQWN5ENNvZ",
            "start_at": {
              "Ms": 26180.0
            },
            "end_at": {
              "Ms": 29000.0
            },
            "camera_angle": {
              "character": {
                "character_pose_emotion": [
                  "피디",
                  "기본",
                  "눈감고곤란"
                ],
                "source_01_circumscribed": {
                  "center": {
                    "x": 0.49375,
                    "y": 0.85555553
                  },
                  "radius": 0.5
                },
                "crop_screen_01_rect": {
                  "Ltrb": {
                    "left": 0.0,
                    "top": 0.0,
                    "right": 1.0,
                    "bottom": 1.0
                  }
                }
              },
              "background": null
            }
          },
          {
            "id": "CameraClip-cGIe0aTCkzmiES5uEL_gQ",
            "start_at": {
              "Ms": 29000.0
            },
            "end_at": {
              "Ms": 32180.0
            },
            "camera_angle": {
              "character": {
                "character_pose_emotion": [
                  "피디",
                  "기본",
                  "눈치"
                ],
                "source_01_circumscribed": {
                  "center": {
                    "x": 0.49375,
                    "y": 0.85555553
                  },
                  "radius": 0.5
                },
                "crop_screen_01_rect": {
                  "Ltrb": {
                    "left": 0.0,
                    "top": 0.0,
                    "right": 1.0,
                    "bottom": 1.0
                  }
                }
              },
              "background": null
            }
          },
          {
            "id": "CameraClip-zydKgAlO4AJ0rpQVsQ1iN",
            "start_at": {
              "Ms": 32180.0
            },
            "end_at": {
              "Ms": 34280.0
            },
            "camera_angle": {
              "character": {
                "character_pose_emotion": [
                  "피디",
                  "기본",
                  "당황웃음"
                ],
                "source_01_circumscribed": {
                  "center": {
                    "x": 0.49375,
                    "y": 0.85555553
                  },
                  "radius": 0.5
                },
                "crop_screen_01_rect": {
                  "Ltrb": {
                    "left": 0.0,
                    "top": 0.0,
                    "right": 1.0,
                    "bottom": 1.0
                  }
                }
              },
              "background": null
            }
          },
          {
            "id": "CameraClip-CqtAFaPJoVzF_s6O0WAT0",
            "start_at": {
              "Ms": 34280.0
            },
            "end_at": {
              "Ms": 38440.0
            },
            "camera_angle": {
              "character": {
                "character_pose_emotion": [
                  "하연",
                  "앉아두손모으고",
                  "걱정"
                ],
                "source_01_circumscribed": {
                  "center": {
                    "x": 0.48333332,
                    "y": 0.65555555
                  },
                  "radius": 0.4326241
                },
                "crop_screen_01_rect": {
                  "Ltrb": {
                    "left": 0.0,
                    "top": 0.0,
                    "right": 1.0,
                    "bottom": 1.0
                  }
                }
              },
              "background": null
            }
          },
          {
            "id": "CameraClip-MbNKWmxA_muI56_9KNPxj",
            "start_at": {
              "Ms": 38440.0
            },
            "end_at": {
              "Ms": 41270.0
            },
            "camera_angle": {
              "character": {
                "character_pose_emotion": [
                  "피디",
                  "기본",
                  "눈감고곤란"
                ],
                "source_01_circumscribed": {
                  "center": {
                    "x": 0.49375,
                    "y": 0.85555553
                  },
                  "radius": 0.5
                },
                "crop_screen_01_rect": {
                  "Ltrb": {
                    "left": 0.0,
                    "top": 0.0,
                    "right": 1.0,
                    "bottom": 1.0
                  }
                }
              },
              "background": null
            }
          },
          {
            "id": "CameraClip-23SJdj6cjsXclitcoFdTK",
            "start_at": {
              "Ms": 41270.0
            },
            "end_at": {
              "Ms": 44240.0
            },
            "camera_angle": {
              "character": {
                "character_pose_emotion": [
                  "피디",
                  "기본",
                  "궁금"
                ],
                "source_01_circumscribed": {
                  "center": {
                    "x": 0.49375,
                    "y": 0.85555553
                  },
                  "radius": 0.5
                },
                "crop_screen_01_rect": {
                  "Ltrb": {
                    "left": 0.0,
                    "top": 0.0,
                    "right": 1.0,
                    "bottom": 1.0
                  }
                }
              },
              "background": null
            }
          },
          {
            "id": "CameraClip-XrX02f9BAQYF6zfAlcs2I",
            "start_at": {
              "Ms": 44240.0
            },
            "end_at": {
              "Ms": 46060.0
            },
            "camera_angle": {
              "character": {
                "character_pose_emotion": [
                  "피디",
                  "기본",
                  "무표정"
                ],
                "source_01_circumscribed": {
                  "center": {
                    "x": 0.49375,
                    "y": 0.85555553
                  },
                  "radius": 0.5
                },
                "crop_screen_01_rect": {
                  "Ltrb": {
                    "left": 0.0,
                    "top": 0.0,
                    "right": 1.0,
                    "bottom": 1.0
                  }
                }
              },
              "background": null
            }
          },
          {
            "id": "CameraClip-G03bNUmSw9bFO2gpdFkZF",
            "start_at": {
              "Ms": 46060.0
            },
            "end_at": {
              "Ms": 48980.0
            },
            "camera_angle": {
              "character": {
                "character_pose_emotion": [
                  "피디",
                  "기본",
                  "당황웃음"
                ],
                "source_01_circumscribed": {
                  "center": {
                    "x": 0.49375,
                    "y": 0.85555553
                  },
                  "radius": 0.5
                },
                "crop_screen_01_rect": {
                  "Ltrb": {
                    "left": 0.0,
                    "top": 0.0,
                    "right": 1.0,
                    "bottom": 1.0
                  }
                }
              },
              "background": null
            }
          },
          {
            "id": "CameraClip-jZutdnMGyMXX3JkaTZ084",
            "start_at": {
              "Ms": 48980.0
            },
            "end_at": {
              "Ms": 50980.0
            },
            "camera_angle": {
              "character": {
                "character_pose_emotion": [
                  "피디",
                  "기본",
                  "활짝웃음"
                ],
                "source_01_circumscribed": {
                  "center": {
                    "x": 0.49375,
                    "y": 0.85555553
                  },
                  "radius": 0.5
                },
                "crop_screen_01_rect": {
                  "Ltrb": {
                    "left": 0.0,
                    "top": 0.0,
                    "right": 1.0,
                    "bottom": 1.0
                  }
                }
              },
              "background": null
            }
          }
        ]
      }
    },
    {
      "Subtitle": {
        "id": "subtitle-track",
        "clips": [
          {
            "id": "2022-02-22-21-38-0001",
            "start_at": {
              "Ms": 30.0
            },
            "subtitle": {
              "id": "2022-02-22-21-38-0001",
              "speaker": "하연",
              "language_text_map": {
                "Ko": "아.. 제가 인터넷 방송을 했었는데…"
              }
            }
          },
          {
            "id": "2022-02-22-21-38-0002",
            "start_at": {
              "Ms": 3140.0002
            },
            "subtitle": {
              "id": "2022-02-22-21-38-0002",
              "speaker": "피디",
              "language_text_map": {
                "Ko": "악플러들이 좌표찍고"
              }
            }
          },
          {
            "id": "2022-02-22-21-38-0003",
            "start_at": {
              "Ms": 4910.0
            },
            "subtitle": {
              "id": "2022-02-22-21-38-0003",
              "speaker": "하연",
              "language_text_map": {
                "Ko": "잘 안됐어요."
              }
            }
          },
          {
            "id": "2022-02-22-21-38-0004",
            "start_at": {
              "Ms": 5990.0
            },
            "subtitle": {
              "id": "2022-02-22-21-38-0004",
              "speaker": "피디",
              "language_text_map": {
                "Ko": "의도적으로 공격을 한 것 같더라고요."
              }
            }
          },
          {
            "id": "2022-02-22-21-38-0005",
            "start_at": {
              "Ms": 8600.0
            },
            "subtitle": {
              "id": "2022-02-22-21-38-0005",
              "speaker": "하연",
              "language_text_map": {
                "Ko": "그냥, 에펙이나… 롤같은거…"
              }
            }
          },
          {
            "id": "2022-02-22-21-38-0006",
            "start_at": {
              "Ms": 10980.001
            },
            "subtitle": {
              "id": "2022-02-22-21-38-0006",
              "speaker": "피디",
              "language_text_map": {
                "Ko": "계속 참다가 대응을 좀 안좋게…"
              }
            }
          },
          {
            "id": "2022-02-22-21-38-0007",
            "start_at": {
              "Ms": 13170.001
            },
            "subtitle": {
              "id": "2022-02-22-21-38-0007",
              "speaker": "하연",
              "language_text_map": {
                "Ko": "방송, 그래도 재미 있었어요!"
              }
            }
          },
          {
            "id": "2022-02-22-21-38-0008",
            "start_at": {
              "Ms": 15200.001
            },
            "subtitle": {
              "id": "2022-02-22-21-38-0008",
              "speaker": "피디",
              "language_text_map": {
                "Ko": "악플러한테 욕을 했어요. 좀 심하게"
              }
            }
          },
          {
            "id": "2022-02-22-21-38-0009",
            "start_at": {
              "Ms": 17160.0
            },
            "subtitle": {
              "id": "2022-02-22-21-38-0009",
              "speaker": "하연",
              "language_text_map": {
                "Ko": "..."
              }
            }
          },
          {
            "id": "2022-02-22-21-38-0010",
            "start_at": {
              "Ms": 18640.0
            },
            "subtitle": {
              "id": "2022-02-22-21-38-0010",
              "speaker": "하연",
              "language_text_map": {
                "Ko": "누가 그래요?"
              }
            }
          },
          {
            "id": "2022-02-22-21-38-0011",
            "start_at": {
              "Ms": 20040.0
            },
            "subtitle": {
              "id": "2022-02-22-21-38-0011",
              "speaker": "피디",
              "language_text_map": {
                "Ko": "이게 좀 말씀드리기 어려운 욕설을…"
              }
            }
          },
          {
            "id": "2022-02-22-21-38-0012",
            "start_at": {
              "Ms": 21940.0
            },
            "subtitle": {
              "id": "2022-02-22-21-38-0012",
              "speaker": "하연",
              "language_text_map": {
                "Ko": "아니 걔네가 먼저 그랬어요!!"
              }
            }
          },
          {
            "id": "2022-02-22-21-38-0013",
            "start_at": {
              "Ms": 23580.0
            },
            "subtitle": {
              "id": "2022-02-22-21-38-0013",
              "speaker": "피디",
              "language_text_map": {
                "Ko": "욕한거 잘라다가 돌아다니니까"
              }
            }
          },
          {
            "id": "2022-02-22-21-38-0014",
            "start_at": {
              "Ms": 26210.0
            },
            "subtitle": {
              "id": "2022-02-22-21-38-0014",
              "speaker": "피디",
              "language_text_map": {
                "Ko": "소속사에서 하연씨를 짜른 것 같더라고요"
              }
            }
          },
          {
            "id": "2022-02-22-21-38-0015",
            "start_at": {
              "Ms": 28980.0
            },
            "subtitle": {
              "id": "2022-02-22-21-38-0015",
              "speaker": "피디",
              "language_text_map": {
                "Ko": "근데 그전에, 거기서 장비를 준 것 같은데"
              }
            }
          },
          {
            "id": "2022-02-22-21-38-0016",
            "start_at": {
              "Ms": 32160.0
            },
            "subtitle": {
              "id": "2022-02-22-21-38-0016",
              "speaker": "피디",
              "language_text_map": {
                "Ko": "그게 무료가 아니고… 강매..."
              }
            }
          },
          {
            "id": "2022-02-22-21-38-0017",
            "start_at": {
              "Ms": 34270.004
            },
            "subtitle": {
              "id": "2022-02-22-21-38-0017",
              "speaker": "하연",
              "language_text_map": {
                "Ko": "..."
              }
            }
          },
          {
            "id": "2022-02-22-21-38-0018",
            "start_at": {
              "Ms": 35810.0
            },
            "subtitle": {
              "id": "2022-02-22-21-38-0018",
              "speaker": "하연",
              "language_text_map": {
                "Ko": "저"
              }
            }
          },
          {
            "id": "2022-02-22-21-38-0019",
            "start_at": {
              "Ms": 37360.0
            },
            "subtitle": {
              "id": "2022-02-22-21-38-0019",
              "speaker": "하연",
              "language_text_map": {
                "Ko": "여기 편집해주시면 안돼요?"
              }
            }
          },
          {
            "id": "2022-02-22-21-38-0020",
            "start_at": {
              "Ms": 38980.0
            },
            "subtitle": {
              "id": "2022-02-22-21-38-0020",
              "speaker": "피디",
              "language_text_map": {
                "Ko": "방송 막 뜰 때 그만뒀으니까…"
              }
            }
          },
          {
            "id": "2022-02-22-21-38-0021",
            "start_at": {
              "Ms": 41260.0
            },
            "subtitle": {
              "id": "2022-02-22-21-38-0021",
              "speaker": "피디",
              "language_text_map": {
                "Ko": "돈 못갚아서 난감한 상황인 것 같아요."
              }
            }
          },
          {
            "id": "2022-02-22-21-38-0022",
            "start_at": {
              "Ms": 44250.0
            },
            "subtitle": {
              "id": "2022-02-22-21-38-0022",
              "speaker": "",
              "language_text_map": {
                "Ko": "Q. 피디님은 어떻게 잘 아세요?"
              }
            }
          },
          {
            "id": "2022-02-22-21-38-0023",
            "start_at": {
              "Ms": 45830.0
            },
            "subtitle": {
              "id": "2022-02-22-21-38-0023",
              "speaker": "피디",
              "language_text_map": {
                "Ko": "저요?"
              }
            }
          },
          {
            "id": "2022-02-22-21-38-0024",
            "start_at": {
              "Ms": 47540.0
            },
            "subtitle": {
              "id": "2022-02-22-21-38-0024",
              "speaker": "피디",
              "language_text_map": {
                "Ko": "…"
              }
            }
          },
          {
            "id": "2022-02-22-21-38-0025",
            "start_at": {
              "Ms": 48980.0
            },
            "subtitle": {
              "id": "2022-02-22-21-38-0025",
              "speaker": "피디",
              "language_text_map": {
                "Ko": "비밀인데, 시청자였어요"
              }
            }
          }
        ]
      }
    }
  ]
}